{"currentPage":1, "perPage": 10, "membersCount":25,
  "members":[
    {"ubcid": 12312312, "name":"Kevin", "department": "Computer Science", "roleid":[1,10], "serviceRole":["RANDOM", "ROLEBRO"], "email":"abc@gmail.com", "status": true},
    {"ubcid": 2, "name":"LL", "department": "Computer Science", "roleid":[2], "serviceRole":["C"], "email":"abc@gmail.com", "status": true},
    {"ubcid": 3, "name":"TEST", "department": "Computer Science", "roleid":[3], "serviceRole":["C"], "email":"aryujbc@gmail.com",  "status": true},
    {"ubcid": 4, "name":"ASD", "department": "Computer Science", "roleid":[4], "serviceRole":["C"], "email":"dfgh@gmail.com",  "status": true},
    {"ubcid": 5, "name":"adsfgdg", "department": "Computer Science", "roleid":[5], "serviceRole":["C"], "email":"abcfgh@gmail.com",  "status": true},
    {"ubcid": 6, "name":"6=WETJI", "department": "Computer Science", "roleid":[6], "serviceRole":["C"], "email":"abc@gmail.com",  "status": false},
    {"ubcid": 7, "name":"SHGR", "department": "Computer Science", "roleid":[2], "serviceRole":["C"], "email":"tysdkjm@gmail.com",  "status": true},
    {"ubcid": 8, "name":"ADPROHN", "department": "Computer Science", "roleid":[3], "serviceRole":["C"], "email":"abc@gmail.com",  "status": true},
    {"ubcid": 9, "name":"ASL{RK", "department": "Computer Science", "roleid":[1], "serviceRole":["C"], "email":"aeur@gmail.com",  "status": false},
    {"ubcid": 10, "name":"10", "department": "Computer Science", "roleid":[5], "serviceRole":["C"], "email":"aert@gmail.com",  "status": true},
    {"ubcid": 11, "name":"OWGSEH", "department": "Computer Science", "roleid":[7], "serviceRole":["C"], "email":"xfgj@gmail.com",  "status": false},
    {"ubcid": 12, "name":"1WE4TRJ[", "department": "Computer Science", "roleid":[4], "serviceRole":["C"], "email":"sdtghf@gmail.com",  "status": true},
    {"ubcid": 13, "name":"1AEIRJPB", "department": "Computer Science", "roleid":[5], "serviceRole":["C"], "email":"dfgj@gmail.com",  "status": true},
    {"ubcid": 14, "name":"2J4P  T", "department": "Computer Science", "roleid":[9], "serviceRole":["C"], "email":"zdfg@gmail.com",  "status": false},
    {"ubcid": 15, "name":"ZDFOBN", "department": "Computer Science", "roleid":[10], "serviceRole":["C"], "email":"jxfhj@gmail.com",  "status": true},
    {"ubcid": 16, "name":"wergkv", "department": "Computer Science", "roleid":[11], "serviceRole":["C"], "email":"jxfg@gmail.com",  "status": true},
    {"ubcid": 17, "name":"WEGIN", "department": "Computer Science", "roleid":[12], "serviceRole":["C"], "email":"abc@gmail.com",  "status": false},
    {"ubcid": 18, "name":"1P[JIDBH", "department": "Computer Science", "roleid":[17], "serviceRole":["C"], "email":"abc@gmail.com",  "status": true},
    {"ubcid": 19, "name":"aerg", "department": "Computer Science", "roleid":[4], "serviceRole":["C"], "email":"abc@gmail.com",  "status": true},
    {"ubcid": 20, "name":"20", "department": "Computer Science", "roleid":[3], "serviceRole":["C"], "email":"abc@gmail.com",  "status": true},
    {"ubcid": 21, "name":"zcvb", "department": "Computer Science", "roleid":[2], "serviceRole":["C"], "email":"abc@gmail.com",  "status": true},
    {"ubcid": 22, "name":"wer4ty", "department": "Computer Science", "roleid":[6], "serviceRole":["C"], "email":"abc@gmail.com",  "status": false},
    {"ubcid": 23, "name":"2qwetr", "department": "Computer Science", "roleid":[2], "serviceRole":["C"], "email":"abc@gmail.com",  "status": true},
    {"ubcid": 24, "name":"2dnb[o", "department": "Computer Science", "roleid":[11], "serviceRole":["C"], "email":"abc@gmail.com",  "status": false},
    {"ubcid": 25, "name":"25", "department": "Computer Science", "roleid":[8], "serviceRole":["C"], "email":"aasdfc@gmail.com",  "status": false}
  ]
}